syncere/__init__.py
syncere/__main__.py
syncere/cliargs.py
syncere/exceptions.py
syncere-0.8.0.dist-info/DESCRIPTION.rst
syncere-0.8.0.dist-info/METADATA
syncere-0.8.0.dist-info/RECORD
syncere-0.8.0.dist-info/WHEEL
syncere-0.8.0.dist-info/entry_points.txt
syncere-0.8.0.dist-info/metadata.json
syncere-0.8.0.dist-info/top_level.txt
