Metadata-Version: 2.0
Name: syncere
Version: 0.8.0
Summary: Interactive rsync-based data synchronization.
Home-page: https://github.com/kynikos/syncere
Author: Dario Giovannetti
Author-email: dev@dariogiovannetti.net
License: GPLv3+
Keywords: rsync synchronization backup files transfer mirroring
Platform: UNKNOWN
Classifier: Development Status :: 4 - Beta
Classifier: Environment :: Console
Classifier: Intended Audience :: System Administrators
Classifier: Topic :: System :: Archiving :: Backup
Classifier: Topic :: System :: Archiving :: Mirroring
Classifier: License :: OSI Approved :: GNU General Public License v3 or later (GPLv3+)
Classifier: Programming Language :: Python :: 3
Requires-Dist: forwarg
Requires-Dist: cmenu
